crpy_tools/__init__.py
crpy_tools/__main__.py
crpy_tools-0.1.1.dist-info/licenses/LICENSE
crpy_tools-0.1.1.dist-info/METADATA
crpy_tools-0.1.1.dist-info/WHEEL
crpy_tools-0.1.1.dist-info/entry_points.txt
crpy_tools-0.1.1.dist-info/top_level.txt
crpy_tools-0.1.1.dist-info/RECORD
