Metadata-Version: 2.4
Name: crpy-tools
Version: 0.1.1
Summary: A CLI and GUI tool built with PySide6
Author-email: Youness <bouness@live.com>
License: MIT License
Project-URL: Homepage, https://github.com/bouness/crpy_tools
Project-URL: Repository, https://github.com/bouness/crpy_tools
Requires-Python: >=3.8
License-File: LICENSE
Requires-Dist: PySide6
Dynamic: license-file
